jit_proxy/__init__.py
jit_proxy/jit_proxy_client.py
jit_proxy/jitter/base_jitter.py
jit_proxy/jitter/jitter_shotgun.py
jit_proxy/jitter/jitter_sniper.py
drift_jit_proxy-0.1.6.dist-info/METADATA
drift_jit_proxy-0.1.6.dist-info/WHEEL
drift_jit_proxy-0.1.6.dist-info/RECORD
