Metadata-Version: 2.1
Name: drift-jit-proxy
Version: 0.1.6
Summary: python sdk for drift protocol v2 jit proxy program
Author: Frank
Author-email: frank@lunoho.company
Requires-Python: >=3.10,<4.0
Classifier: Programming Language :: Python :: 3
Classifier: Programming Language :: Python :: 3.10
Classifier: Programming Language :: Python :: 3.11
Requires-Dist: anchorpy (>=0.20.1,<0.21.0)
Requires-Dist: driftpy (>=0.7.0)
Requires-Dist: python-dotenv (>=1.0.0,<2.0.0)
Requires-Dist: solana (>=0.34.0,<0.35.0)
